snnw/__init__.py
snnw/run.py
snnw/dataset/__init__.py
snnw/dataset/mnist/__init__.py
snnw/dataset/mnist/convert.py
snnw/dataset/mnist/download.py
snnw/nn/__init__.py
snnw/nn/config.py
snnw/nn/layer.py
snnw/nn/model.py
snnw/nn/weight_init.py
snnw/nn/activation/__init__.py
snnw/nn/activation/relu.py
snnw/nn/activation/sigmoid.py
snnw/nn/activation/softmax.py
snnw/nn/activation/tanh.py
snnw/nn/loss/__init__.py
snnw/nn/loss/cross_entropy.py
snnw-0.2.8.dist-info/LICENSE
snnw-0.2.8.dist-info/METADATA
snnw-0.2.8.dist-info/WHEEL
snnw-0.2.8.dist-info/top_level.txt
snnw-0.2.8.dist-info/RECORD
