Metadata-Version: 2.1
Name: snnw
Version: 0.2.8
Summary: My custom neural net architecture written in Python to practice my ML skills.
Home-page: https://github.com/juliustao/Slowest-Neural-Net-in-the-West
Author: Julius Tao
Author-email: juliusltao@gmail.com
License: MIT
Platform: UNKNOWN
Classifier: License :: OSI Approved :: MIT License
Classifier: Programming Language :: Python
Classifier: Programming Language :: Python :: 3
Classifier: Programming Language :: Python :: 3.6
Classifier: Programming Language :: Python :: Implementation :: CPython
Classifier: Programming Language :: Python :: Implementation :: PyPy
Requires-Python: >=3.6.0
Requires-Dist: numpy (==1.18.1)
Requires-Dist: pypng (==0.0.20)
Requires-Dist: Pillow (==7.0.0)
Requires-Dist: tqdm (==4.42.1)
